ufal.nametag.libs/libstdc++-a9383cce.so.6.0.28
ufal.nametag.libs/libgcc_s-a04fdf82.so.1
ufal.nametag-1.2.1.1.dist-info/top_level.txt
ufal.nametag-1.2.1.1.dist-info/WHEEL
ufal.nametag-1.2.1.1.dist-info/METADATA
ufal.nametag-1.2.1.1.dist-info/LICENSE
ufal.nametag-1.2.1.1.dist-info/RECORD
ufal/__init__.py
ufal/nametag/__init__.py
ufal/nametag/_nametag.cpython-39-x86_64-linux-gnu.so
